diff/__init__.py
diffinder_Leon_Green-0.7.dist-info/LICENSE
diffinder_Leon_Green-0.7.dist-info/METADATA
diffinder_Leon_Green-0.7.dist-info/WHEEL
diffinder_Leon_Green-0.7.dist-info/top_level.txt
diffinder_Leon_Green-0.7.dist-info/RECORD
