Metadata-Version: 2.1
Name: diffinder-Leon-Green
Version: 0.7
Summary: Difference finder for reports
Home-page: UNKNOWN
Author: Leon Green
Author-email: author@example.com
License: UNKNOWN
Platform: UNKNOWN
Classifier: Programming Language :: Python :: 3
Classifier: License :: OSI Approved :: MIT License
Classifier: Operating System :: OS Independent
Requires-Python: >=3.6
